{"bbc-news":{"word_length":{"1":1,"14":1,"13":2,"10":4,"9":8,"2":10,"8":13,"6":17,"3":17,"7":26,"5":26,"4":30},"title_length":{"7":1,"8":2,"6":6,"4":8,"5":9,"3":13,"2":17},"popular_words":{"bbc":{"word":"bbc","weighted":39,"occurances":7},"news":{"word":"news","weighted":34,"occurances":6},"for":{"word":"for","weighted":29,"occurances":5},"in":{"word":"in","weighted":28,"occurances":5},"live":{"word":"live","weighted":21,"occurances":4},"on":{"word":"on","weighted":21,"occurances":4},"the":{"word":"the","weighted":17,"occurances":3},"to":{"word":"to","weighted":17,"occurances":3},"world":{"word":"world","weighted":16,"occurances":3},"could":{"word":"could","weighted":16,"occurances":3}},"popular_words_non_joining":{"news":{"word":"news","weighted":34,"occurances":6},"live":{"word":"live","weighted":21,"occurances":4},"world":{"word":"world","weighted":16,"occurances":3},"could":{"word":"could","weighted":16,"occurances":3},"links":{"word":"links","weighted":12,"occurances":2},"local":{"word":"local","weighted":11,"occurances":2},"pictures":{"word":"pictures","weighted":11,"occurances":2},"obama":{"word":"obama","weighted":6,"occurances":1},"children":{"word":"children","weighted":6,"occurances":1},"sorry":{"word":"sorry","weighted":6,"occurances":1}}},"telegraph":{"word_length":{"12":2,"13":4,"1":8,"11":9,"10":16,"2":27,"9":33,"8":50,"3":64,"7":81,"6":105,"4":119,"5":122},"title_length":{"15":1,"18":1,"14":1,"12":2,"13":2,"11":6,"2":6,"3":7,"10":9,"8":12,"7":16,"9":16,"4":19,"5":26,"6":31},"popular_words":{"the":{"word":"the","weighted":244,"occurances":41},"to":{"word":"to","weighted":131,"occurances":22},"of":{"word":"of","weighted":119,"occurances":20},"in":{"word":"in","weighted":114,"occurances":19},"a":{"word":"a","weighted":108,"occurances":18},"for":{"word":"for","weighted":84,"occurances":14},"on":{"word":"on","weighted":72,"occurances":12},"is":{"word":"is","weighted":60,"occurances":10},"and":{"word":"and","weighted":54,"occurances":9},"north":{"word":"north","weighted":42,"occurances":7}},"popular_words_non_joining":{"north":{"word":"north","weighted":42,"occurances":7},"korea":{"word":"korea","weighted":42,"occurances":7},"more":{"word":"more","weighted":36,"occurances":6},"city":{"word":"city","weighted":36,"occurances":6},"home":{"word":"home","weighted":30,"occurances":5},"guide":{"word":"guide","weighted":30,"occurances":5},"week":{"word":"week","weighted":30,"occurances":5},"your":{"word":"your","weighted":30,"occurances":5},"pictures":{"word":"pictures","weighted":24,"occurances":4},"world":{"word":"world","weighted":24,"occurances":4}}},"sun":{"word_length":{"15":1,"14":2,"13":2,"12":6,"1":7,"11":9,"10":19,"2":33,"9":37,"8":66,"3":92,"7":121,"6":162,"5":191,"4":207},"title_length":{"21":1,"17":1,"27":1,"23":1,"3":2,"20":2,"16":3,"2":3,"5":3,"7":4,"15":4,"14":9,"6":10,"13":12,"11":14,"12":14,"8":28,"9":36,"10":36},"popular_words":{"to":{"word":"to","weighted":117,"occurances":39},"a":{"word":"a","weighted":105,"occurances":35},"in":{"word":"in","weighted":102,"occurances":34},"the":{"word":"the","weighted":96,"occurances":31},"of":{"word":"of","weighted":81,"occurances":27},"for":{"word":"for","weighted":69,"occurances":22},"at":{"word":"at","weighted":63,"occurances":21},"is":{"word":"is","weighted":63,"occurances":21},"and":{"word":"and","weighted":57,"occurances":19},"with":{"word":"with","weighted":57,"occurances":19}},"popular_words_non_joining":{"star":{"word":"star","weighted":27,"occurances":9},"after":{"word":"after","weighted":27,"occurances":9},"back":{"word":"back","weighted":24,"occurances":8},"their":{"word":"their","weighted":24,"occurances":8},"from":{"word":"from","weighted":21,"occurances":7},"body":{"word":"body","weighted":21,"occurances":7},"that":{"word":"that","weighted":18,"occurances":6},"look":{"word":"look","weighted":18,"occurances":6},"bikini":{"word":"bikini","weighted":18,"occurances":6},"home":{"word":"home","weighted":15,"occurances":5}}},"daily-mail":{"word_length":{"14":1,"1":4,"12":5,"13":8,"11":13,"2":30,"10":39,"9":65,"3":92,"8":95,"7":152,"4":169,"6":171,"5":181},"title_length":{"11":1,"10":1,"30":1,"12":1,"8":1,"6":1,"28":1,"4":1,"31":2,"2":2,"15":2,"26":2,"5":3,"21":4,"13":4,"24":4,"27":5,"23":5,"3":6,"16":6,"22":6,"19":7,"14":7,"20":7,"17":11,"18":11},"popular_words":{"the":{"word":"the","weighted":302,"occurances":51},"to":{"word":"to","weighted":258,"occurances":43},"a":{"word":"a","weighted":228,"occurances":38},"of":{"word":"of","weighted":219,"occurances":37},"in":{"word":"in","weighted":214,"occurances":36},"and":{"word":"and","weighted":186,"occurances":31},"for":{"word":"for","weighted":174,"occurances":29},"after":{"word":"after","weighted":132,"occurances":22},"as":{"word":"as","weighted":96,"occurances":16},"is":{"word":"is","weighted":96,"occurances":16}},"popular_words_non_joining":{"after":{"word":"after","weighted":132,"occurances":22},"from":{"word":"from","weighted":78,"occurances":13},"that":{"word":"that","weighted":47,"occurances":8},"over":{"word":"over","weighted":42,"occurances":7},"years":{"word":"years","weighted":42,"occurances":7},"than":{"word":"than","weighted":36,"occurances":6},"they":{"word":"they","weighted":36,"occurances":6},"year":{"word":"year","weighted":36,"occurances":6},"your":{"word":"your","weighted":36,"occurances":6},"more":{"word":"more","weighted":36,"occurances":6}}},"independent":{"word_length":{"13":2,"12":4,"1":7,"11":11,"10":22,"9":37,"2":38,"3":41,"8":49,"6":70,"7":73,"5":90,"4":96},"title_length":{"17":1,"16":1,"15":1,"12":2,"19":2,"14":2,"18":3,"8":6,"10":7,"9":7,"7":7,"11":9,"5":11,"6":12,"4":14,"3":18,"2":23},"popular_words":{"the":{"word":"the","weighted":120,"occurances":27},"a":{"word":"a","weighted":76,"occurances":17},"of":{"word":"of","weighted":71,"occurances":16},"to":{"word":"to","weighted":62,"occurances":14},"london":{"word":"london","weighted":50,"occurances":10},"in":{"word":"in","weighted":49,"occurances":11},"for":{"word":"for","weighted":36,"occurances":8},"sw":{"word":"sw","weighted":35,"occurances":7},"as":{"word":"as","weighted":32,"occurances":7},"is":{"word":"is","weighted":31,"occurances":7}},"popular_words_non_joining":{"london":{"word":"london","weighted":50,"occurances":10},"green":{"word":"green","weighted":25,"occurances":5},"their":{"word":"their","weighted":15,"occurances":3},"best":{"word":"best","weighted":15,"occurances":3},"britain":{"word":"britain","weighted":15,"occurances":3},"kent":{"word":"kent","weighted":15,"occurances":3},"hits":{"word":"hits","weighted":15,"occurances":3},"great":{"word":"great","weighted":14,"occurances":3},"north":{"word":"north","weighted":13,"occurances":3},"design":{"word":"design","weighted":12,"occurances":3}}},"the-times":{"word_length":{"15":1,"14":2,"13":3,"11":3,"12":4,"1":4,"10":6,"9":13,"2":18,"8":33,"3":35,"7":46,"4":52,"6":53,"5":63},"title_length":{"12":1,"11":2,"9":4,"3":6,"10":6,"4":7,"5":7,"6":9,"7":10,"2":12,"8":13},"popular_words":{"the":{"word":"the","weighted":48,"occurances":16},"in":{"word":"in","weighted":38,"occurances":12},"for":{"word":"for","weighted":34,"occurances":10},"on":{"word":"on","weighted":30,"occurances":10},"of":{"word":"of","weighted":30,"occurances":10},"times":{"word":"times","weighted":27,"occurances":9},"to":{"word":"to","weighted":23,"occurances":7},"and":{"word":"and","weighted":21,"occurances":7},"at":{"word":"at","weighted":21,"occurances":7},"a":{"word":"a","weighted":15,"occurances":5}},"popular_words_non_joining":{"times":{"word":"times","weighted":27,"occurances":9},"woman":{"word":"woman","weighted":10,"occurances":2},"luxury":{"word":"luxury","weighted":9,"occurances":3},"film":{"word":"film","weighted":9,"occurances":3},"save":{"word":"save","weighted":9,"occurances":3},"business":{"word":"business","weighted":9,"occurances":3},"holiday":{"word":"holiday","weighted":9,"occurances":3},"life":{"word":"life","weighted":9,"occurances":3},"korea":{"word":"korea","weighted":8,"occurances":2},"over":{"word":"over","weighted":8,"occurances":2}}}}