{"the":{"weighted":191,"occurances":32},"to":{"weighted":114,"occurances":19},"for":{"weighted":102,"occurances":17},"of":{"weighted":83,"occurances":14},"in":{"weighted":66,"occurances":11},"at":{"weighted":59,"occurances":10},"a":{"weighted":54,"occurances":9},"boston":{"weighted":53,"occurances":9},"on":{"weighted":48,"occurances":8},"and":{"weighted":47,"occurances":8},"as":{"weighted":42,"occurances":7},"marathon":{"weighted":41,"occurances":7},"with":{"weighted":36,"occurances":6},"london":{"weighted":35,"occurances":6},"is":{"weighted":30,"occurances":5},"new":{"weighted":30,"occurances":5},"how":{"weighted":30,"occurances":5},"korea":{"weighted":30,"occurances":5},"be":{"weighted":30,"occurances":5},"best":{"weighted":30,"occurances":5},"most":{"weighted":24,"occurances":4},"novelists":{"weighted":24,"occurances":4},"chelsea":{"weighted":24,"occurances":4},"british":{"weighted":24,"occurances":4},"not":{"weighted":18,"occurances":3},"world":{"weighted":18,"occurances":3},"funeral":{"weighted":18,"occurances":3},"hold":{"weighted":18,"occurances":3},"you":{"weighted":18,"occurances":3},"what":{"weighted":18,"occurances":3},"prepare":{"weighted":18,"occurances":3},"thatchers":{"weighted":18,"occurances":3},"its":{"weighted":18,"occurances":3},"six":{"weighted":18,"occurances":3},"race":{"weighted":18,"occurances":3},"andrew":{"weighted":18,"occurances":3},"now":{"weighted":18,"occurances":3},"young":{"weighted":18,"occurances":3},"show":{"weighted":18,"occurances":3},"plants":{"weighted":18,"occurances":3},"north":{"weighted":18,"occurances":3},"was":{"weighted":18,"occurances":3},"thatcher":{"weighted":12,"occurances":2},"guide":{"weighted":12,"occurances":2},"granta":{"weighted":12,"occurances":2},"royal":{"weighted":12,"occurances":2},"kate":{"weighted":12,"occurances":2},"from":{"weighted":12,"occurances":2},"unveiled":{"weighted":12,"occurances":2},"big":{"weighted":12,"occurances":2},"aircraft":{"weighted":12,"occurances":2},"has":{"weighted":12,"occurances":2},"tick":{"weighted":12,"occurances":2},"cat":{"weighted":12,"occurances":2},"only":{"weighted":12,"occurances":2},"davis":{"weighted":12,"occurances":2},"colin":{"weighted":12,"occurances":2},"recalls":{"weighted":12,"occurances":2},"glorious":{"weighted":12,"occurances":2},"mccann":{"weighted":12,"occurances":2},"next":{"weighted":12,"occurances":2},"whats":{"weighted":12,"occurances":2},"pictures":{"weighted":12,"occurances":2},"himself":{"weighted":12,"occurances":2},"years":{"weighted":12,"occurances":2},"attack":{"weighted":12,"occurances":2},"sir":{"weighted":12,"occurances":2},"hillsborough":{"weighted":12,"occurances":2},"they":{"weighted":12,"occurances":2},"mean":{"weighted":12,"occurances":2},"future":{"weighted":12,"occurances":2},"by":{"weighted":12,"occurances":2},"back":{"weighted":12,"occurances":2},"wenger":{"weighted":12,"occurances":2},"f":{"weighted":12,"occurances":2},"must":{"weighted":12,"occurances":2},"have":{"weighted":12,"occurances":2},"website":{"weighted":12,"occurances":2},"living":{"weighted":12,"occurances":2},"this":{"weighted":12,"occurances":2},"dreadful":{"weighted":12,"occurances":2},"test":{"weighted":12,"occurances":2},"everton":{"weighted":12,"occurances":2},"void":{"weighted":12,"occurances":2},"n":{"weighted":12,"occurances":2},"uk":{"weighted":12,"occurances":2},"upton":{"weighted":12,"occurances":2},"spotlight":{"weighted":12,"occurances":2},"art":{"weighted":12,"occurances":2},"waxworks":{"weighted":12,"occurances":2},"stadium":{"weighted":12,"occurances":2},"victims":{"weighted":12,"occurances":2},"full":{"weighted":12,"occurances":2},"among":{"weighted":12,"occurances":2},"our":{"weighted":12,"occurances":2},"city":{"weighted":12,"occurances":2},"tragedy":{"weighted":12,"occurances":2},"eightyearold":{"weighted":12,"occurances":2},"blown":{"weighted":12,"occurances":2},"behind":{"weighted":12,"occurances":2},"bombs":{"weighted":12,"occurances":2},"why":{"weighted":12,"occurances":2},"will":{"weighted":12,"occurances":2},"it":{"weighted":12,"occurances":2},"britons":{"weighted":12,"occurances":2},"dead":{"weighted":12,"occurances":2},"unfolded":{"weighted":12,"occurances":2},"marathons":{"weighted":12,"occurances":2},"makes":{"weighted":12,"occurances":2},"maestro":{"weighted":12,"occurances":2},"off":{"weighted":12,"occurances":2},"course":{"weighted":12,"occurances":2},"injured":{"weighted":12,"occurances":2},"three":{"weighted":12,"occurances":2},"safety":{"weighted":11,"occurances":2},"inflation":{"weighted":11,"occurances":2},"explosions":{"weighted":11,"occurances":2},"high":{"weighted":11,"occurances":2},"runner":{"weighted":11,"occurances":2},"surfers":{"weighted":6,"occurances":1},"procession":{"weighted":6,"occurances":1},"route":{"weighted":6,"occurances":1},"details":{"weighted":6,"occurances":1},"standings":{"weighted":6,"occurances":1},"carpet":{"weighted":6,"occurances":1},"stamps":{"weighted":6,"occurances":1},"great":{"weighted":6,"occurances":1},"bombing":{"weighted":6,"occurances":1},"red":{"weighted":6,"occurances":1},"style":{"weighted":6,"occurances":1},"awards":{"weighted":6,"occurances":1},"movie":{"weighted":6,"occurances":1},"mtv":{"weighted":6,"occurances":1},"underwater":{"weighted":6,"occurances":1},"south":{"weighted":6,"occurances":1},"ever":{"weighted":6,"occurances":1},"twitter":{"weighted":6,"occurances":1},"penalty":{"weighted":6,"occurances":1},"worst":{"weighted":6,"occurances":1},"football":{"weighted":6,"occurances":1},"match":{"weighted":6,"occurances":1},"music":{"weighted":6,"occurances":1},"coming":{"weighted":6,"occurances":1},"fines":{"weighted":6,"occurances":1},"smartphone":{"weighted":6,"occurances":1},"judge":{"weighted":6,"occurances":1},"officially":{"weighted":6,"occurances":1},"soon":{"weighted":6,"occurances":1},"dutch":{"weighted":6,"occurances":1},"during":{"weighted":6,"occurances":1},"horror":{"weighted":6,"occurances":1},"prepares":{"weighted":6,"occurances":1},"belsen":{"weighted":6,"occurances":1},"boy":{"weighted":6,"occurances":1},"remembered":{"weighted":6,"occurances":1},"veteran":{"weighted":6,"occurances":1},"gorillas":{"weighted":6,"occurances":1},"battle":{"weighted":6,"occurances":1},"stops":{"weighted":6,"occurances":1},"play":{"weighted":6,"occurances":1},"viral":{"weighted":6,"occurances":1},"goes":{"weighted":6,"occurances":1},"goose":{"weighted":6,"occurances":1},"calendar":{"weighted":6,"occurances":1},"inside":{"weighted":6,"occurances":1},"episode":{"weighted":6,"occurances":1},"paul":{"weighted":6,"occurances":1},"s":{"weighted":6,"occurances":1},"thrones":{"weighted":6,"occurances":1},"house":{"weighted":6,"occurances":1},"game":{"weighted":6,"occurances":1},"hollywoods":{"weighted":6,"occurances":1},"bread":{"weighted":6,"occurances":1},"dozens":{"weighted":6,"occurances":1},"judges":{"weighted":6,"occurances":1},"shock":{"weighted":6,"occurances":1},"fbi":{"weighted":6,"occurances":1},"hunts":{"weighted":6,"occurances":1},"opera":{"weighted":6,"occurances":1},"nabucco":{"weighted":6,"occurances":1},"pulitzer":{"weighted":6,"occurances":1},"prize":{"weighted":6,"occurances":1},"miller":{"weighted":6,"occurances":1},"joe":{"weighted":6,"occurances":1},"couple":{"weighted":6,"occurances":1},"broadchurch":{"weighted":6,"occurances":1},"winner":{"weighted":6,"occurances":1},"fiction":{"weighted":6,"occurances":1},"gagosian":{"weighted":6,"occurances":1},"gallery":{"weighted":6,"occurances":1},"whiteread":{"weighted":6,"occurances":1},"rachel":{"weighted":6,"occurances":1},"announced":{"weighted":6,"occurances":1},"view":{"weighted":6,"occurances":1},"surprises":{"weighted":6,"occurances":1},"disruption":{"weighted":6,"occurances":1},"visit":{"weighted":6,"occurances":1},"face":{"weighted":6,"occurances":1},"visitors":{"weighted":6,"occurances":1},"victim":{"weighted":6,"occurances":1},"interiors":{"weighted":6,"occurances":1},"tour":{"weighted":6,"occurances":1},"mood":{"weighted":6,"occurances":1},"weird":{"weighted":6,"occurances":1},"reasons":{"weighted":6,"occurances":1},"glimpse":{"weighted":6,"occurances":1},"spectacular":{"weighted":6,"occurances":1},"use":{"weighted":6,"occurances":1},"named":{"weighted":6,"occurances":1},"break":{"weighted":6,"occurances":1},"punchdrunk":{"weighted":6,"occurances":1},"drowned":{"weighted":6,"occurances":1},"under":{"weighted":6,"occurances":1},"list":{"weighted":6,"occurances":1},"grantas":{"weighted":6,"occurances":1},"diverse":{"weighted":6,"occurances":1},"man":{"weighted":6,"occurances":1},"trailer":{"weighted":6,"occurances":1},"roots":{"weighted":6,"occurances":1},"bath":{"weighted":6,"occurances":1},"hampshire":{"weighted":6,"occurances":1},"austens":{"weighted":6,"occurances":1},"jane":{"weighted":6,"occurances":1},"delays":{"weighted":6,"occurances":1},"wine":{"weighted":6,"occurances":1},"five":{"weighted":6,"occurances":1},"yearolds":{"weighted":6,"occurances":1},"shakespeare":{"weighted":6,"occurances":1},"genes":{"weighted":6,"occurances":1},"runners":{"weighted":6,"occurances":1},"evil":{"weighted":6,"occurances":1},"shami":{"weighted":6,"occurances":1},"chakrabarti":{"weighted":6,"occurances":1},"attacked":{"weighted":6,"occurances":1},"over":{"weighted":6,"occurances":1},"coalition":{"weighted":6,"occurances":1},"lse":{"weighted":6,"occurances":1},"disowns":{"weighted":6,"occurances":1},"genetic":{"weighted":6,"occurances":1},"kidney":{"weighted":6,"occurances":1},"bursting":{"weighted":6,"occurances":1},"colour":{"weighted":6,"occurances":1},"homes":{"weighted":6,"occurances":1},"sale":{"weighted":6,"occurances":1},"top":{"weighted":6,"occurances":1},"flats":{"weighted":6,"occurances":1},"slug":{"weighted":6,"occurances":1},"invasion":{"weighted":6,"occurances":1},"first":{"weighted":6,"occurances":1},"labgrown":{"weighted":6,"occurances":1},"roundup":{"weighted":6,"occurances":1},"news":{"weighted":6,"occurances":1},"flower":{"weighted":6,"occurances":1},"atomised":{"weighted":6,"occurances":1},"curriculum":{"weighted":6,"occurances":1},"find":{"weighted":6,"occurances":1},"out":{"weighted":6,"occurances":1},"collection":{"weighted":6,"occurances":1},"shrub":{"weighted":6,"occurances":1},"dwarf":{"weighted":6,"occurances":1},"flowering":{"weighted":6,"occurances":1},"toyota":{"weighted":6,"occurances":1},"prius":{"weighted":6,"occurances":1},"capitals":{"weighted":6,"occurances":1},"schools":{"weighted":6,"occurances":1},"equipment":{"weighted":6,"occurances":1},"sports":{"weighted":6,"occurances":1},"bringing":{"weighted":6,"occurances":1},"bestseller":{"weighted":6,"occurances":1},"gives":{"weighted":6,"occurances":1},"addiction":{"weighted":6,"occurances":1},"pink":{"weighted":6,"occurances":1},"drug":{"weighted":6,"occurances":1},"lucrative":{"weighted":6,"occurances":1},"marnell":{"weighted":6,"occurances":1},"mums":{"weighted":6,"occurances":1},"career":{"weighted":6,"occurances":1},"card":{"weighted":6,"occurances":1},"that":{"weighted":6,"occurances":1},"charge":{"weighted":6,"occurances":1},"computer":{"weighted":6,"occurances":1},"history":{"weighted":6,"occurances":1},"histories":{"weighted":6,"occurances":1},"unusual":{"weighted":6,"occurances":1},"hm":{"weighted":6,"occurances":1},"holiday":{"weighted":6,"occurances":1},"beyonces":{"weighted":6,"occurances":1},"seed":{"weighted":6,"occurances":1},"quinoa":{"weighted":6,"occurances":1},"cookfriendly":{"weighted":6,"occurances":1},"spirit":{"weighted":6,"occurances":1},"wore":{"weighted":6,"occurances":1},"i":{"weighted":6,"occurances":1},"got":{"weighted":6,"occurances":1},"essentials":{"weighted":6,"occurances":1},"nail":{"weighted":6,"occurances":1},"coachella":{"weighted":6,"occurances":1},"review":{"weighted":6,"occurances":1},"restaurant":{"weighted":6,"occurances":1},"competition":{"weighted":6,"occurances":1},"offer":{"weighted":6,"occurances":1},"search":{"weighted":6,"occurances":1},"google":{"weighted":6,"occurances":1},"regulators":{"weighted":6,"occurances":1},"agree":{"weighted":6,"occurances":1},"english":{"weighted":6,"occurances":1},"bomber":{"weighted":6,"occurances":1},"holder":{"weighted":6,"occurances":1},"lyndhurst":{"weighted":6,"occurances":1},"hartnett":{"weighted":6,"occurances":1},"splash":{"weighted":6,"occurances":1},"making":{"weighted":6,"occurances":1},"im":{"weighted":6,"occurances":1},"celebrity":{"weighted":6,"occurances":1},"truth":{"weighted":6,"occurances":1},"car":{"weighted":6,"occurances":1},"fastest":{"weighted":6,"occurances":1},"worlds":{"weighted":6,"occurances":1},"bugatti":{"weighted":6,"occurances":1},"reinstated":{"weighted":6,"occurances":1},"victor":{"weighted":6,"occurances":1},"carranza":{"weighted":6,"occurances":1},"brodrick":{"weighted":6,"occurances":1},"properties":{"weighted":6,"occurances":1},"les":{"weighted":6,"occurances":1},"lieutenant":{"weighted":6,"occurances":1},"flight":{"weighted":6,"occurances":1},"menu":{"weighted":6,"occurances":1},"cars":{"weighted":6,"occurances":1},"all":{"weighted":6,"occurances":1},"phones":{"weighted":6,"occurances":1},"free":{"weighted":6,"occurances":1},"numbers":{"weighted":6,"occurances":1},"freephone":{"weighted":6,"occurances":1},"britains":{"weighted":6,"occurances":1},"complained":{"weighted":6,"occurances":1},"classic":{"weighted":6,"occurances":1},"touring":{"weighted":6,"occurances":1},"firms":{"weighted":6,"occurances":1},"financial":{"weighted":6,"occurances":1},"about":{"weighted":6,"occurances":1},"eu":{"weighted":6,"occurances":1},"tussauds":{"weighted":6,"occurances":1},"gold":{"weighted":6,"occurances":1},"ticks":{"weighted":6,"occurances":1},"below":{"weighted":6,"occurances":1},"falls":{"weighted":6,"occurances":1},"month":{"weighted":6,"occurances":1},"oil":{"weighted":6,"occurances":1},"higher":{"weighted":6,"occurances":1},"bailey":{"weighted":6,"occurances":1},"avoided":{"weighted":6,"occurances":1},"formal":{"weighted":6,"occurances":1},"bosses":{"weighted":6,"occurances":1},"bank":{"weighted":6,"occurances":1},"odd":{"weighted":6,"occurances":1},"holds":{"weighted":6,"occurances":1},"near":{"weighted":6,"occurances":1},"appear":{"weighted":6,"occurances":1},"harry":{"weighted":6,"occurances":1},"despite":{"weighted":6,"occurances":1},"fears":{"weighted":6,"occurances":1},"blairites":{"weighted":6,"occurances":1},"prince":{"weighted":6,"occurances":1},"hard":{"weighted":6,"occurances":1},"helicopter":{"weighted":6,"occurances":1},"crashes":{"weighted":6,"occurances":1},"us":{"weighted":6,"occurances":1},"policing":{"weighted":6,"occurances":1},"so":{"weighted":6,"occurances":1},"charges":{"weighted":6,"occurances":1},"greece":{"weighted":6,"occurances":1},"guarantee":{"weighted":6,"occurances":1},"media":{"weighted":6,"occurances":1},"no":{"weighted":6,"occurances":1},"logistics":{"weighted":6,"occurances":1},"reaction":{"weighted":6,"occurances":1},"wont":{"weighted":6,"occurances":1},"climate":{"weighted":6,"occurances":1},"suspicion":{"weighted":6,"occurances":1},"blasts":{"weighted":6,"occurances":1},"webb":{"weighted":6,"occurances":1},"blast":{"weighted":6,"occurances":1},"senator":{"weighted":6,"occurances":1},"athletics":{"weighted":6,"occurances":1},"direction":{"weighted":6,"occurances":1},"one":{"weighted":6,"occurances":1},"paula":{"weighted":6,"occurances":1},"principle":{"weighted":6,"occurances":1},"workers":{"weighted":6,"occurances":1},"state":{"weighted":6,"occurances":1},"sack":{"weighted":6,"occurances":1},"women":{"weighted":6,"occurances":1},"arent":{"weighted":6,"occurances":1},"cable":{"weighted":6,"occurances":1},"didnt":{"weighted":6,"occurances":1},"work":{"weighted":6,"occurances":1},"ahead":{"weighted":6,"occurances":1},"getting":{"weighted":6,"occurances":1},"dissenting":{"weighted":6,"occurances":1},"loyalty":{"weighted":6,"occurances":1},"protest":{"weighted":6,"occurances":1},"cross":{"weighted":6,"occurances":1},"does":{"weighted":6,"occurances":1},"when":{"weighted":6,"occurances":1},"piece":{"weighted":6,"occurances":1},"last":{"weighted":6,"occurances":1},"line":{"weighted":6,"occurances":1},"bieber":{"weighted":6,"occurances":1},"anne":{"weighted":6,"occurances":1},"frank":{"weighted":6,"occurances":1},"secondguess":{"weighted":6,"occurances":1},"get":{"weighted":6,"occurances":1},"doesnt":{"weighted":6,"occurances":1},"heir":{"weighted":6,"occurances":1},"advice":{"weighted":6,"occurances":1},"expose":{"weighted":6,"occurances":1},"barbs":{"weighted":6,"occurances":1},"frailty":{"weighted":6,"occurances":1},"labour":{"weighted":6,"occurances":1},"unity":{"weighted":6,"occurances":1},"blairite":{"weighted":6,"occurances":1},"pauls":{"weighted":6,"occurances":1},"positioned":{"weighted":6,"occurances":1},"pm":{"weighted":6,"occurances":1},"pew":{"weighted":6,"occurances":1},"farage":{"weighted":6,"occurances":1},"st":{"weighted":6,"occurances":1},"developing":{"weighted":6,"occurances":1},"turned":{"weighted":6,"occurances":1},"pig":{"weighted":6,"occurances":1},"born":{"weighted":6,"occurances":1},"rehearsal":{"weighted":6,"occurances":1},"dawn":{"weighted":6,"occurances":1},"mark":{"weighted":6,"occurances":1},"respect":{"weighted":6,"occurances":1},"using":{"weighted":6,"occurances":1},"feared":{"weighted":6,"occurances":1},"miliband":{"weighted":6,"occurances":1},"demands":{"weighted":6,"occurances":1},"ed":{"weighted":6,"occurances":1},"approach":{"weighted":6,"occurances":1},"gm":{"weighted":6,"occurances":1},"silent":{"weighted":6,"occurances":1},"fall":{"weighted":6,"occurances":1},"calls":{"weighted":6,"occurances":1},"dignified":{"weighted":6,"occurances":1},"weston":{"weighted":6,"occurances":1},"simon":{"weighted":6,"occurances":1},"thatcherite":{"weighted":6,"occurances":1},"response":{"weighted":6,"occurances":1},"body":{"weighted":6,"occurances":1},"service":{"weighted":6,"occurances":1},"ben":{"weighted":6,"occurances":1},"private":{"weighted":6,"occurances":1},"chapel":{"weighted":6,"occurances":1},"moved":{"weighted":6,"occurances":1},"exiled":{"weighted":6,"occurances":1},"shocked":{"weighted":6,"occurances":1},"forced":{"weighted":6,"occurances":1},"quit":{"weighted":6,"occurances":1},"may":{"weighted":6,"occurances":1},"showed":{"weighted":6,"occurances":1},"welsh":{"weighted":6,"occurances":1},"say":{"weighted":6,"occurances":1},"kassam":{"weighted":6,"occurances":1},"telegraph":{"weighted":6,"occurances":1},"accessfree":{"weighted":6,"occurances":1},"day":{"weighted":6,"occurances":1},"clock":{"weighted":6,"occurances":1},"packunlimited":{"weighted":6,"occurances":1},"web":{"weighted":6,"occurances":1},"relegated":{"weighted":6,"occurances":1},"games":{"weighted":6,"occurances":1},"colchester":{"weighted":6,"occurances":1},"families":{"weighted":6,"occurances":1},"pays":{"weighted":6,"occurances":1},"henry":{"weighted":6,"occurances":1},"john":{"weighted":6,"occurances":1},"ennis":{"weighted":6,"occurances":1},"set":{"weighted":6,"occurances":1},"sainsburys":{"weighted":6,"occurances":1},"anniversary":{"weighted":6,"occurances":1},"return":{"weighted":6,"occurances":1},"then":{"weighted":6,"occurances":1},"olympic":{"weighted":6,"occurances":1},"trial":{"weighted":6,"occurances":1},"commented":{"weighted":6,"occurances":1},"made":{"weighted":6,"occurances":1},"headlines":{"weighted":6,"occurances":1},"maggie":{"weighted":6,"occurances":1},"fear":{"weighted":6,"occurances":1},"describe":{"weighted":6,"occurances":1},"chaos":{"weighted":6,"occurances":1},"madame":{"weighted":6,"occurances":1},"like":{"weighted":6,"occurances":1},"houston":{"weighted":6,"occurances":1},"pain":{"weighted":6,"occurances":1},"whitney":{"weighted":6,"occurances":1},"misses":{"weighted":6,"occurances":1},"hits":{"weighted":6,"occurances":1},"witnesses":{"weighted":6,"occurances":1},"grammar":{"weighted":6,"occurances":1},"charles":{"weighted":6,"occurances":1},"saatchi":{"weighted":6,"occurances":1},"who":{"weighted":6,"occurances":1},"viewed":{"weighted":6,"occurances":1},"shared":{"weighted":6,"occurances":1},"launches":{"weighted":6,"occurances":1},"playful":{"weighted":6,"occurances":1},"pass":{"weighted":6,"occurances":1},"good":{"weighted":6,"occurances":1},"can":{"weighted":6,"occurances":1},"coverage":{"weighted":6,"occurances":1},"mysterious":{"weighted":6,"occurances":1},"owner":{"weighted":6,"occurances":1},"tribute":{"weighted":6,"occurances":1},"arsenal":{"weighted":6,"occurances":1},"v":{"weighted":6,"occurances":1},"scalps":{"weighted":6,"occurances":1},"need":{"weighted":6,"occurances":1},"early":{"weighted":6,"occurances":1},"justice":{"weighted":6,"occurances":1},"preview":{"weighted":6,"occurances":1},"players":{"weighted":6,"occurances":1},"soothes":{"weighted":6,"occurances":1},"aussie":{"weighted":6,"occurances":1},"scott":{"weighted":6,"occurances":1},"liverpool":{"weighted":6,"occurances":1},"nerve":{"weighted":6,"occurances":1},"too":{"weighted":6,"occurances":1},"rushed":{"weighted":6,"occurances":1},"violence":{"weighted":6,"occurances":1},"after":{"weighted":6,"occurances":1},"fans":{"weighted":6,"occurances":1},"plea":{"weighted":6,"occurances":1},"newcastle":{"weighted":6,"occurances":1},"snowball":{"weighted":6,"occurances":1},"ugly":{"weighted":6,"occurances":1},"finishes":{"weighted":6,"occurances":1},"wilshere":{"weighted":6,"occurances":1},"crisis":{"weighted":6,"occurances":1},"but":{"weighted":6,"occurances":1},"scenes":{"weighted":6,"occurances":1},"angst":{"weighted":6,"occurances":1},"adam":{"weighted":6,"occurances":1},"psg":{"weighted":6,"occurances":1},"hopes":{"weighted":6,"occurances":1},"masters":{"weighted":6,"occurances":1},"rotation":{"weighted":6,"occurances":1},"maintain":{"weighted":6,"occurances":1},"dashed":{"weighted":6,"occurances":1},"wayne":{"weighted":6,"occurances":1},"manchester":{"weighted":6,"occurances":1},"united":{"weighted":6,"occurances":1},"hit":{"weighted":6,"occurances":1},"pledges":{"weighted":6,"occurances":1},"rooney":{"weighted":6,"occurances":1},"bentez":{"weighted":6,"occurances":1},"policy":{"weighted":6,"occurances":1},"bernie":{"weighted":6,"occurances":1},"ecclestone":{"weighted":6,"occurances":1},"rafael":{"weighted":6,"occurances":1},"promises":{"weighted":6,"occurances":1},"victory":{"weighted":6,"occurances":1},"plays":{"weighted":6,"occurances":1},"chief":{"weighted":6,"occurances":1},"manager":{"weighted":6,"occurances":1},"down":{"weighted":6,"occurances":1},"obama":{"weighted":6,"occurances":1},"interim":{"weighted":6,"occurances":1},"bahrain":{"weighted":6,"occurances":1},"protests":{"weighted":6,"occurances":1},"spectator":{"weighted":5,"occurances":1},"ensuring":{"weighted":5,"occurances":1},"mile":{"weighted":5,"occurances":1},"difficulty":{"weighted":5,"occurances":1},"keeping":{"weighted":5,"occurances":1},"goods":{"weighted":5,"occurances":1},"stubbornly":{"weighted":5,"occurances":1},"underline":{"weighted":5,"occurances":1},"enormous":{"weighted":5,"occurances":1}}