{"bbc-news":{"word_length":{"1":1,"14":1,"13":1,"11":1,"12":2,"10":3,"9":6,"8":11,"3":14,"2":15,"7":19,"5":26,"6":29,"4":31},"title_length":{"7":4,"4":6,"5":8,"6":8,"3":14,"2":17},"popular_words":{"to":{"word":"to","weighted":34,"occurances":6},"news":{"word":"news","weighted":34,"occurances":6},"bbc":{"word":"bbc","weighted":33,"occurances":6},"live":{"word":"live","weighted":31,"occurances":6},"of":{"word":"of","weighted":28,"occurances":5},"in":{"word":"in","weighted":27,"occurances":5},"the":{"word":"the","weighted":23,"occurances":4},"baroness":{"word":"baroness","weighted":17,"occurances":3},"uk":{"word":"uk","weighted":12,"occurances":2},"links":{"word":"links","weighted":12,"occurances":2}},"popular_words_non_joining":{"news":{"word":"news","weighted":34,"occurances":6},"live":{"word":"live","weighted":31,"occurances":6},"baroness":{"word":"baroness","weighted":17,"occurances":3},"links":{"word":"links","weighted":12,"occurances":2},"stories":{"word":"stories","weighted":12,"occurances":2},"home":{"word":"home","weighted":11,"occurances":2},"pictures":{"word":"pictures","weighted":11,"occurances":2},"world":{"word":"world","weighted":11,"occurances":2},"local":{"word":"local","weighted":11,"occurances":2},"thatcher":{"word":"thatcher","weighted":11,"occurances":2}}},"telegraph":{"word_length":{"14":1,"13":3,"12":3,"1":5,"11":9,"9":19,"10":20,"2":28,"3":54,"8":68,"7":75,"5":86,"6":88,"4":107},"title_length":{"14":1,"13":1,"23":1,"11":3,"10":6,"2":6,"8":10,"3":11,"9":11,"7":16,"4":20,"5":26,"6":28},"popular_words":{"the":{"word":"the","weighted":160,"occurances":27},"to":{"word":"to","weighted":120,"occurances":20},"for":{"word":"for","weighted":90,"occurances":15},"of":{"word":"of","weighted":82,"occurances":14},"in":{"word":"in","weighted":78,"occurances":13},"a":{"word":"a","weighted":60,"occurances":10},"funeral":{"word":"funeral","weighted":60,"occurances":10},"on":{"word":"on","weighted":48,"occurances":8},"at":{"word":"at","weighted":41,"occurances":7},"and":{"word":"and","weighted":36,"occurances":6}},"popular_words_non_joining":{"funeral":{"word":"funeral","weighted":60,"occurances":10},"margaret":{"word":"margaret","weighted":36,"occurances":6},"thatcher":{"word":"thatcher","weighted":36,"occurances":6},"thatchers":{"word":"thatchers","weighted":30,"occurances":5},"worlds":{"word":"worlds","weighted":30,"occurances":5},"united":{"word":"united","weighted":30,"occurances":5},"most":{"word":"most","weighted":30,"occurances":5},"full":{"word":"full","weighted":24,"occurances":4},"biggest":{"word":"biggest","weighted":24,"occurances":4},"pauls":{"word":"pauls","weighted":24,"occurances":4}}},"sun":{"word_length":{"18":1,"13":2,"1":4,"12":5,"11":8,"10":20,"9":30,"2":32,"8":72,"3":105,"7":132,"6":166,"4":190,"5":208},"title_length":{"18":1,"22":1,"20":1,"3":1,"5":1,"2":2,"14":5,"15":5,"6":6,"13":7,"12":18,"7":20,"11":22,"8":26,"10":34,"9":40},"popular_words":{"to":{"word":"to","weighted":123,"occurances":41},"for":{"word":"for","weighted":99,"occurances":32},"the":{"word":"the","weighted":96,"occurances":31},"in":{"word":"in","weighted":90,"occurances":30},"of":{"word":"of","weighted":81,"occurances":27},"a":{"word":"a","weighted":75,"occurances":25},"on":{"word":"on","weighted":69,"occurances":22},"with":{"word":"with","weighted":57,"occurances":19},"after":{"word":"after","weighted":48,"occurances":16},"and":{"word":"and","weighted":45,"occurances":15}},"popular_words_non_joining":{"after":{"word":"after","weighted":48,"occurances":16},"star":{"word":"star","weighted":30,"occurances":10},"boston":{"word":"boston","weighted":30,"occurances":10},"free":{"word":"free","weighted":24,"occurances":7},"back":{"word":"back","weighted":21,"occurances":7},"sexy":{"word":"sexy","weighted":15,"occurances":5},"boobs":{"word":"boobs","weighted":15,"occurances":5},"show":{"word":"show","weighted":15,"occurances":5},"just":{"word":"just","weighted":15,"occurances":5},"from":{"word":"from","weighted":15,"occurances":5}}},"daily-mail":{"word_length":{"15":1,"13":3,"1":4,"12":11,"11":23,"2":25,"10":33,"9":55,"3":89,"8":96,"7":137,"4":163,"5":165,"6":199},"title_length":{"4":1,"2":1,"6":1,"29":1,"32":1,"10":2,"25":2,"14":3,"13":3,"19":4,"24":4,"23":5,"26":5,"3":5,"12":6,"5":6,"20":7,"17":8,"16":10,"22":10,"18":11,"21":14},"popular_words":{"the":{"word":"the","weighted":290,"occurances":49},"to":{"word":"to","weighted":282,"occurances":47},"of":{"word":"of","weighted":273,"occurances":46},"and":{"word":"and","weighted":228,"occurances":38},"a":{"word":"a","weighted":222,"occurances":37},"in":{"word":"in","weighted":196,"occurances":33},"after":{"word":"after","weighted":192,"occurances":32},"for":{"word":"for","weighted":186,"occurances":31},"on":{"word":"on","weighted":144,"occurances":24},"her":{"word":"her","weighted":144,"occurances":24}},"popular_words_non_joining":{"after":{"word":"after","weighted":192,"occurances":32},"from":{"word":"from","weighted":114,"occurances":19},"their":{"word":"their","weighted":54,"occurances":9},"life":{"word":"life","weighted":48,"occurances":8},"that":{"word":"that","weighted":48,"occurances":8},"years":{"word":"years","weighted":42,"occurances":7},"home":{"word":"home","weighted":36,"occurances":6},"down":{"word":"down","weighted":36,"occurances":6},"being":{"word":"being","weighted":36,"occurances":6},"left":{"word":"left","weighted":36,"occurances":6}}},"independent":{"word_length":{"23":1,"13":2,"14":2,"12":4,"11":6,"1":7,"10":21,"9":27,"2":37,"8":41,"3":44,"7":65,"6":86,"4":90,"5":97},"title_length":{"20":1,"15":2,"12":3,"7":4,"16":5,"6":5,"5":5,"13":5,"14":5,"8":6,"9":6,"10":7,"11":9,"4":15,"3":15,"2":29},"popular_words":{"the":{"word":"the","weighted":140,"occurances":31},"to":{"word":"to","weighted":76,"occurances":17},"a":{"word":"a","weighted":59,"occurances":12},"in":{"word":"in","weighted":55,"occurances":12},"is":{"word":"is","weighted":53,"occurances":12},"london":{"word":"london","weighted":49,"occurances":10},"of":{"word":"of","weighted":40,"occurances":9},"sw":{"word":"sw","weighted":35,"occurances":7},"for":{"word":"for","weighted":35,"occurances":8},"as":{"word":"as","weighted":33,"occurances":8}},"popular_words_non_joining":{"london":{"word":"london","weighted":49,"occurances":10},"from":{"word":"from","weighted":24,"occurances":5},"thatcher":{"word":"thatcher","weighted":20,"occurances":4},"suffolk":{"word":"suffolk","weighted":20,"occurances":4},"have":{"word":"have","weighted":16,"occurances":4},"british":{"word":"british","weighted":15,"occurances":3},"battersea":{"word":"battersea","weighted":15,"occurances":3},"james":{"word":"james","weighted":15,"occurances":3},"about":{"word":"about","weighted":15,"occurances":3},"green":{"word":"green","weighted":15,"occurances":3}}},"the-times":{"word_length":{"13":1,"11":3,"1":3,"12":5,"10":6,"9":14,"2":23,"8":26,"3":38,"5":46,"6":51,"4":56,"7":57},"title_length":{"11":1,"10":6,"3":6,"8":8,"6":8,"4":8,"5":9,"9":9,"7":11,"2":13},"popular_words":{"the":{"word":"the","weighted":68,"occurances":22},"times":{"word":"times","weighted":24,"occurances":8},"to":{"word":"to","weighted":24,"occurances":8},"for":{"word":"for","weighted":21,"occurances":7},"in":{"word":"in","weighted":21,"occurances":7},"thatcher":{"word":"thatcher","weighted":20,"occurances":6},"with":{"word":"with","weighted":18,"occurances":6},"of":{"word":"of","weighted":18,"occurances":6},"a":{"word":"a","weighted":15,"occurances":5},"funeral":{"word":"funeral","weighted":13,"occurances":3}},"popular_words_non_joining":{"times":{"word":"times","weighted":24,"occurances":8},"thatcher":{"word":"thatcher","weighted":20,"occurances":6},"funeral":{"word":"funeral","weighted":13,"occurances":3},"film":{"word":"film","weighted":12,"occurances":4},"island":{"word":"island","weighted":9,"occurances":3},"celebrate":{"word":"celebrate","weighted":9,"occurances":3},"from":{"word":"from","weighted":9,"occurances":3},"business":{"word":"business","weighted":9,"occurances":3},"thatchers":{"word":"thatchers","weighted":8,"occurances":2},"over":{"word":"over","weighted":8,"occurances":2}}}}